{
  "_format": "hh-sol-cache-2",
  "files": {
    "/Users/apple/Desktop/PG/NadVault/contracts/MysteryBoxLaunchpad.sol": {
      "lastModificationDate": 1740511462964,
      "contentHash": "d15441941210ae5eca7eaa5eedb39a54",
      "sourceName": "contracts/MysteryBoxLaunchpad.sol",
      "solcConfig": {
        "version": "0.8.0",
        "settings": {
          "optimizer": {
            "enabled": false,
            "runs": 200
          },
          "outputSelection": {
            "*": {
              "*": [
                "abi",
                "evm.bytecode",
                "evm.deployedBytecode",
                "evm.methodIdentifiers",
                "metadata"
              ],
              "": [
                "ast"
              ]
            }
          }
        }
      },
      "imports": [],
      "versionPragmas": [
        "^0.8.0"
      ],
      "artifacts": [
        "MysteryBoxLaunchpad"
      ]
    },
    "/Users/apple/Desktop/PG/NadVault/contracts/TokenLockup.sol": {
      "lastModificationDate": 1740511472364,
      "contentHash": "c4f918b73544588d364624c1f70b75e4",
      "sourceName": "contracts/TokenLockup.sol",
      "solcConfig": {
        "version": "0.8.0",
        "settings": {
          "optimizer": {
            "enabled": false,
            "runs": 200
          },
          "outputSelection": {
            "*": {
              "*": [
                "abi",
                "evm.bytecode",
                "evm.deployedBytecode",
                "evm.methodIdentifiers",
                "metadata"
              ],
              "": [
                "ast"
              ]
            }
          }
        }
      },
      "imports": [],
      "versionPragmas": [
        "^0.8.0"
      ],
      "artifacts": [
        "IERC20",
        "TokenLockup"
      ]
    }
  }
}
